[
    {
      "id": 1,
      "estate_title": "Luxury Beachfront Hotel",
      "image": "https://assets-global.website-files.com/5c6d6c45eaa55f57c6367749/65045f093c166fdddb4a94a5_x-65045f0266217.webp",
      "segment_name": "Hotels",
      "description": "Experience unparalleled luxury at our beachfront hotel. Enjoy stunning ocean views, world-class amenities, and impeccable service.",
      "price": 2500.00,
      "status": "sale",
      "Area": "3000 sq ft",
      "location": "Miami Beach, Florida",
      "facilities": [
        "Living Room",
        "Swimming Pool",
        "Kitchen (in select suites)",
        "Spa",
        "Fitness Center",
        "Multiple Restaurants and Bars"
      ]
    },
    {
      "id": 2,
      "estate_title": "Cozy Mountain Cabin",
      "image": "https://images.ctfassets.net/pqmtoyw9z10u/1aPC1wGWG7wbP5rIbR9i8S/b9206a5c5a57996362e756e888e269de/pexels-thanhhoa-tran-1488327.jpg",
      "segment_name": "Vacation Rentals",
      "description": "Relax and unwind in our charming mountain cabin. Perfect for a romantic getaway or a family vacation.",
      "price": 120.00,
      "status": "rent",
      "Area": "1500 sq ft",
      "location": "Lake Tahoe, California",
      "facilities": [
        "Living Room with Fireplace",
        "Fully Equipped Kitchen",
        "Deck with Hot Tub",
        "BBQ Grill"
      ]
    },
    {
      "id": 3,
      "estate_title": "Modern City Apartment",
      "image": "https://encrypted-tbn0.gstatic.com/images?q=tbn:ANd9GcRy9ez500NMeyJeFfePPbkLVh_xnOrF9fgyeo9DxaBePQ&s",
      "segment_name": "Lodges",
      "description": "Live in the heart of the city in our modern apartment building. Enjoy stunning city views and convenient access to all that the city has to offer.",
      "price": 1800.00,
      "status": "sale",
      "Area": "1000 sq ft",
      "location": "New York City, New York",
      "facilities": [
        "Living Room",
        "Kitchen",
        "Fitness Center",
        "Rooftop Terrace"
      ]
    },
    {
      "id": 4,
      "estate_title": "Tropical Island Resort",
      "image": "https://encrypted-tbn0.gstatic.com/images?q=tbn:ANd9GcT8qiGWIQDWiMC_z7lar3b0cw4dx1RObhgsS5CIQ5NWtg&s",
      "segment_name": "Resorts",
      "description": "Escape to paradise at our all-inclusive resort. Enjoy pristine beaches, luxurious accommodations, and endless activities.",
      "price": 300.00,
      "status": "rent",
      "Area": "Varies (bungalows, suites)",
      "location": "Maldives, Asia",
      "facilities": [
        "Multiple Swimming Pools",
        "Private Beach Access",
        "Multiple Restaurants and Bars",
        "Spa",
        "Fitness Center",
        "Kids Club"
      ]
    },
    {
      "id": 5,
      "estate_title": "Charming Bed and Breakfast",
      "image": "https://cf.bstatic.com/xdata/images/hotel/max1024x768/38289896.jpg?k=0ffe9712c7e60237daf2e6c5e30ef8034f46f3ea565353ec50c76291fdee7f8f&o=&hp=1",
      "segment_name": "Guesthouses",
      "description": "Experience a taste of home at our charming bed and breakfast. Enjoy personalized service and a relaxing atmosphere.",
      "price": 100.00,
      "status": "rent",
      "Area": "800 sq ft",
      "location": "London, England",
      "facilities": [
        "Shared Living Room",
        "Breakfast Included",
        "Laundry Facilities"
      ]
    },
    {
      "id": 6,
      "estate_title": "Budget-Friendly Motel",
      "image": "https://media.gq.com/photos/5a60cffa1aa9696e38a74768/16:9/w_2560%2Cc_limit/2018-01_GQ_RenovatedMotels_3x2.jpg",
      "segment_name": "Motels",
      "description": "A clean and comfortable place to stay on your travels. Convenient location and affordable rates.",
      "price": 600.00,
      "status": "sale",
      "Area": "500 sq ft",
      "location": "Route 66, Arizona",
      "facilities": [
        "Parking",
        "Wi-Fi",
        "Cable TV"
      ]
    }
  ]
  